creditscoringpy/__init__.py
creditscoringpy/creditscoringpy.py
creditscoringpy-0.1.0.dist-info/LICENSE
creditscoringpy-0.1.0.dist-info/METADATA
creditscoringpy-0.1.0.dist-info/WHEEL
creditscoringpy-0.1.0.dist-info/top_level.txt
creditscoringpy-0.1.0.dist-info/RECORD
